orbl_onpremise/__init__.py
orbl_onpremise/asm/__init__.py
orbl_onpremise/asm/v1.py
orbl_onpremise/auth/__init__.py
orbl_onpremise/auth/v1.py
orbl_onpremise/auth_token.py
orbl_onpremise/base.py
orbl_onpremise/clients.py
orbl_onpremise/compare/__init__.py
orbl_onpremise/compare/v1.py
orbl_onpremise/constants.py
orbl_onpremise/entries/__init__.py
orbl_onpremise/entries/v1.py
orbl_onpremise/groups_profiles/__init__.py
orbl_onpremise/groups_profiles/v1.py
orbl_onpremise/licenses/__init__.py
orbl_onpremise/licenses/v1.py
orbl_onpremise/liveness/__init__.py
orbl_onpremise/liveness/v1.py
orbl_onpremise/origins/__init__.py
orbl_onpremise/origins/v1.py
orbl_onpremise/profiles/__init__.py
orbl_onpremise/profiles/v1.py
orbl_onpremise/spaces/__init__.py
orbl_onpremise/spaces/v1.py
orbl_onpremise/statistics/__init__.py
orbl_onpremise/statistics/v1.py
orbl_onpremise/tokens/__init__.py
orbl_onpremise/tokens/access/__init__.py
orbl_onpremise/tokens/access/v1.py
orbl_onpremise/tokens/streams/__init__.py
orbl_onpremise/tokens/streams/v1.py
orbl_onpremise/users/__init__.py
orbl_onpremise/users/v1.py
orbl_onpremise/utils.py
orbl_onpremise/whoami/__init__.py
orbl_onpremise/whoami/v1.py
orbl_onpremise-0.1.1.dist-info/LICENSE
orbl_onpremise-0.1.1.dist-info/WHEEL
orbl_onpremise-0.1.1.dist-info/METADATA
orbl_onpremise-0.1.1.dist-info/RECORD
