Metadata-Version: 2.1
Name: orbl-onpremise
Version: 0.1.1
Summary: A Python package for interacting with ORBL on-premise API
License: MIT
Requires-Python: >=3.7.0,<4.0.0
Classifier: License :: OSI Approved :: MIT License
Classifier: Programming Language :: Python :: 3
Classifier: Programming Language :: Python :: 3.7
Classifier: Programming Language :: Python :: 3.8
Classifier: Programming Language :: Python :: 3.9
Classifier: Programming Language :: Python :: 3.10
Classifier: Programming Language :: Python :: 3.11
Requires-Dist: httpx (>=0.19.0)
Requires-Dist: websockets (>=10.0,<11.0)
